[
	{
		"name": "react-bootstrap-accordion",
		"keywords": ["accordion", "react", "frontend", "bootstrap", "javascript"],
		"url": "https://github.com/awran5/react-bootstrap-accordion",
		"description": "A simple accordion component for React using Bootstrap styles.",
		"note": 3
	},
	{
		"name": "react-accessible-accordion",
		"keywords": ["accordion", "react", "frontend", "javascript"],
		"url": "https://github.com/springload/react-accessible-accordion",
		"description": "A simple accordion component for React using ARIA attributes.",
		"note": 4
	}
]
